stockfish/__init__.py
stockfish/models.py
stockfish-4.0.3.dist-info/licenses/LICENSE
stockfish-4.0.3.dist-info/METADATA
stockfish-4.0.3.dist-info/WHEEL
stockfish-4.0.3.dist-info/top_level.txt
stockfish-4.0.3.dist-info/RECORD
