Metadata-Version: 2.4
Name: stockfish
Version: 4.0.3
Summary: Wraps the open-source Stockfish chess engine for easy integration into python.
Home-page: https://github.com/py-stockfish/stockfish
Author: Ilya Zhelyabuzhsky
Author-email: zhelyabuzhsky@icloud.com
License: MIT
Keywords: chess stockfish
Classifier: Programming Language :: Python
Classifier: Natural Language :: English
Classifier: Operating System :: Unix
Classifier: License :: OSI Approved :: MIT License
Classifier: Development Status :: 5 - Production/Stable
Classifier: Topic :: Games/Entertainment :: Board Games
Classifier: Topic :: Software Development :: Libraries :: Python Modules
Classifier: Programming Language :: Python :: 3.8
Classifier: Programming Language :: Python :: 3.9
Classifier: Programming Language :: Python :: 3.10
Classifier: Programming Language :: Python :: 3.11
Classifier: Programming Language :: Python :: 3.12
Classifier: Programming Language :: Python :: 3.13
Classifier: Programming Language :: Python :: 3.14
Classifier: Programming Language :: Python :: Implementation :: CPython
Requires-Python: >=3.10
License-File: LICENSE
Dynamic: author
Dynamic: author-email
Dynamic: classifier
Dynamic: description
Dynamic: description-content-type
Dynamic: home-page
Dynamic: keywords
Dynamic: license
Dynamic: license-file
Dynamic: requires-python
Dynamic: summary
